switchblade/__init__.py
switchblade/augmentations.py
switchblade/data.py
switchblade/debugging.py
switchblade/logging.py
switchblade/utils.py
switchblade/audio_datasets/__init__.py
switchblade/audio_datasets/audio_dataset.py
switchblade/audio_datasets/constants.py
switchblade/audio_datasets/dataset.py
switchblade/audio_datasets/discox.py
switchblade/audio_datasets/emomusic.py
switchblade/audio_datasets/get_dataset.py
switchblade/audio_datasets/giantsteps.py
switchblade/audio_datasets/gtzan.py
switchblade/audio_datasets/magnatagatune.py
switchblade/audio_datasets/nsynth.py
switchblade/audio_datasets/tad.py
switchblade/audio_datasets/test.py
switchblade/audio_datasets/utils.py
switchblade/modules/__init__.py
switchblade-0.2.12.dist-info/LICENSE
switchblade-0.2.12.dist-info/METADATA
switchblade-0.2.12.dist-info/WHEEL
switchblade-0.2.12.dist-info/top_level.txt
switchblade-0.2.12.dist-info/RECORD
