Metadata-Version: 2.1
Name: switchblade
Version: 0.2.12
Summary: Deep learning / Music AI utilities for PyTorch
Author-email: Ori Yonay <oriyonay12@gmail.com>
Project-URL: Homepage, https://github.com/oriyonay/switchblade
Project-URL: Bug Tracker, https://github.com/oriyonay/switchblade/issues
Classifier: Programming Language :: Python :: 3
Classifier: License :: OSI Approved :: MIT License
Classifier: Operating System :: OS Independent
Requires-Python: >=3.7
License-File: LICENSE
